duowen_workflow/__init__.py
duowen_workflow/engine.py
duowen_workflow/entities.py
duowen_workflow/nodes/__init__.py
duowen_workflow/nodes/builtin.py
duowen_workflow/utils.py
duowen_workflow-0.1.0.dist-info/METADATA
duowen_workflow-0.1.0.dist-info/WHEEL
duowen_workflow-0.1.0.dist-info/RECORD
