Metadata-Version: 2.3
Name: duowen-workflow
Version: 0.1.0
Summary: 
Author: liurui
Author-email: liurui@asiainfo.com
Requires-Python: >=3.11
Classifier: Programming Language :: Python :: 3
Classifier: Programming Language :: Python :: 3.11
Classifier: Programming Language :: Python :: 3.12
Classifier: Programming Language :: Python :: 3.13
Requires-Dist: jinja2 (>=3.1.6)
Requires-Dist: pydantic (>=2.10.6)
